{"examples_battery.md":"nsGZMthN","examples_codes.md":"BVpUnqR_","examples_hardware-health.md":"D_Wl2fcm","examples_history.md":"DW55kVcJ","examples_index.md":"dp21DxMY","examples_initialization.md":"C-mqA7Rr","examples_nfc.md":"6hNAO_bq","examples_offline-pins.md":"12aPuCEr","examples_open-door.md":"B7jYDroT","examples_packet-visualizer.md":"DezjedOS","examples_regeneration.md":"D_wKs3O0","fr_examples_battery.md":"BbUYbrCp","fr_examples_codes.md":"CvKnYTBM","fr_examples_hardware-health.md":"DvjADqYO","fr_examples_history.md":"oJ9r4hTo","fr_examples_index.md":"BjNeEcTU","fr_examples_initialization.md":"D6m1g5s1","fr_examples_nfc.md":"CpBdJ6ta","fr_examples_offline-pins.md":"DZAHVxAN","fr_examples_open-door.md":"DYbQCqPD","fr_examples_packet-visualizer.md":"CPBZ_Lwk","fr_examples_regeneration.md":"Bctp8I5m","fr_guide_create_user_tag.md":"uY1AGC9B","fr_guide_credentials.md":"C4-sXK9Q","fr_guide_dfu.md":"CL9Ffrzf","fr_guide_firmware-history.md":"BmLJheba","fr_guide_glossary.md":"XbvaAiwN","fr_guide_index.md":"D8vwLvk2","fr_guide_pin-algorithm.md":"D-T2hWDQ","fr_guide_protocol.md":"Cmh4uNPj","fr_guide_quirks.md":"h9b7oVrS","fr_guide_safety.md":"HfHvYu8s","fr_index.md":"Byb6_DEL","guide_create_user_tag.md":"By3MGtHq","guide_credentials.md":"CggYJi3m","guide_dfu.md":"C5gSSs2U","guide_firmware-history.md":"Dc1QUQTT","guide_glossary.md":"1MacjFYA","guide_index.md":"DmVkmS2O","guide_pin-algorithm.md":"DzXqixhz","guide_protocol.md":"BZH1hdnU","guide_quirks.md":"uS6ksejg","guide_safety.md":"o0YE3y3h","index.md":"D78yHAMi"}
