{"examples_battery.md":"atJles62","examples_codes.md":"CNABkdxW","examples_dfu.md":"D5T5VfBV","examples_hardware-health.md":"B2oSN0I3","examples_history.md":"KTqOLScP","examples_index.md":"DRTOBkgr","examples_initialization.md":"DiWuhvn5","examples_nfc.md":"BIy8DtiH","examples_offline-pins.md":"-illPixX","examples_open-door.md":"CTAz-_Zt","examples_regeneration.md":"By1KvjT0","fr_examples_battery.md":"Bhvd6w9l","fr_examples_codes.md":"xyZk99Yt","fr_examples_dfu.md":"CkqycASJ","fr_examples_hardware-health.md":"CfHOY5x4","fr_examples_history.md":"i1aM45XM","fr_examples_index.md":"CEOwpH1d","fr_examples_initialization.md":"CN8ZIdKY","fr_examples_nfc.md":"CnFCBK90","fr_examples_offline-pins.md":"DYpbamah","fr_examples_open-door.md":"DaiO8JUM","fr_examples_regeneration.md":"pnLWOazQ","fr_guide_create_user_tag.md":"DqCY5Lyx","fr_guide_credentials.md":"3g453mJS","fr_guide_dfu.md":"ukm3x8tZ","fr_guide_firmware-history.md":"BiP8zOEs","fr_guide_glossary.md":"ugWVjpuJ","fr_guide_index.md":"DJfduqJc","fr_guide_pin-algorithm.md":"D_JMUT_l","fr_guide_protocol.md":"DYmIJqU0","fr_guide_quirks.md":"wvRBkK5_","fr_guide_safety.md":"DFi5yx6e","fr_index.md":"CBXFC3qy","guide_create_user_tag.md":"C3ow7DaF","guide_credentials.md":"BUgzIKlR","guide_dfu.md":"B-b_DETi","guide_firmware-history.md":"DDUxaSpW","guide_glossary.md":"ygxF2w7b","guide_index.md":"DoeWJe7h","guide_pin-algorithm.md":"DFe72KVL","guide_protocol.md":"BerpynUd","guide_quirks.md":"BU2xTqER","guide_safety.md":"mpzY3IHN","index.md":"vCN5WfKZ"}
