{"examples_battery.md":"nzh8yJ8W","examples_codes.md":"CkvoyyCc","examples_history.md":"D3AH0SPF","examples_index.md":"CSL9Yp5x","examples_initialization.md":"CLw0YlB7","examples_nfc.md":"zGBnNJLH","examples_open-door.md":"D2FxqYix","fr_examples_codes.md":"ip8bil0i","fr_examples_history.md":"CHCZwIXb","fr_examples_nfc.md":"BOE9-biB","fr_guide_credentials.md":"DvbH7kPx","fr_guide_firmware-history.md":"K-1A_53f","fr_guide_glossary.md":"BYsVJQzz","fr_guide_index.md":"JVPoL_SK","fr_guide_pin-algorithm.md":"DjDpmzU6","fr_guide_protocol.md":"CuO4Gb-v","fr_guide_quirks.md":"BFZgB1yU","fr_guide_safety.md":"CrEQ8yk_","fr_index.md":"DDl60sSS","guide_credentials.md":"B6q4XeXx","guide_firmware-history.md":"C56USr3e","guide_glossary.md":"t_ovG2z-","guide_index.md":"DO35VSPc","guide_pin-algorithm.md":"CvSIYQXZ","guide_protocol.md":"B88B5ax8","guide_quirks.md":"B-fjUoKM","guide_safety.md":"CcbnIxpE","index.md":"CWQc0mSk"}
